<?xml version="1.0" encoding="UTF-8"?>
<!DOCTYPE mapper PUBLIC "-//mybatis.org//DTD Mapper 3.0//EN" "http://mybatis.org/dtd/mybatis-3-mapper.dtd">
<mapper namespace="com.lkjc.consumablesmanager.mapper.SysConfigMapper">
  <resultMap id="BaseResultMap" type="com.lkjc.consumablesmanager.entity.SysConfig">
    <!--
      WARNING - @mbg.generated
      This element is automatically generated by MyBatis Generator, do not modify.
    -->
    <id column="SYS_CONFIG_ID" jdbcType="VARCHAR" property="sysConfigId" />
    <result column="NAME" jdbcType="VARCHAR" property="name" />
    <result column="CUR_VALUE" jdbcType="VARCHAR" property="curValue" />
    <result column="VALUE_DESC" jdbcType="VARCHAR" property="valueDesc" />
  </resultMap>
  <delete id="deleteByPrimaryKey" parameterType="java.lang.String">
    <!--
      WARNING - @mbg.generated
      This element is automatically generated by MyBatis Generator, do not modify.
    -->
    delete from sys_config
    where SYS_CONFIG_ID = #{sysConfigId,jdbcType=VARCHAR}
  </delete>
  <insert id="insert" parameterType="com.lkjc.consumablesmanager.entity.SysConfig">
    <!--
      WARNING - @mbg.generated
      This element is automatically generated by MyBatis Generator, do not modify.
    -->
    insert into sys_config (SYS_CONFIG_ID, NAME, CUR_VALUE, 
      VALUE_DESC)
    values (#{sysConfigId,jdbcType=VARCHAR}, #{name,jdbcType=VARCHAR}, #{curValue,jdbcType=VARCHAR}, 
      #{valueDesc,jdbcType=VARCHAR})
  </insert>
  <update id="updateByPrimaryKey" parameterType="com.lkjc.consumablesmanager.entity.SysConfig">
    <!--
      WARNING - @mbg.generated
      This element is automatically generated by MyBatis Generator, do not modify.
    -->
    update sys_config
    set NAME = #{name,jdbcType=VARCHAR},
      CUR_VALUE = #{curValue,jdbcType=VARCHAR},
      VALUE_DESC = #{valueDesc,jdbcType=VARCHAR}
    where SYS_CONFIG_ID = #{sysConfigId,jdbcType=VARCHAR}
  </update>
  <select id="selectByPrimaryKey" parameterType="java.lang.String" resultMap="BaseResultMap">
    <!--
      WARNING - @mbg.generated
      This element is automatically generated by MyBatis Generator, do not modify.
    -->
    select SYS_CONFIG_ID, NAME, CUR_VALUE, VALUE_DESC
    from sys_config
    where SYS_CONFIG_ID = #{sysConfigId,jdbcType=VARCHAR}
  </select>
  <select id="selectAll" resultMap="BaseResultMap">
    <!--
      WARNING - @mbg.generated
      This element is automatically generated by MyBatis Generator, do not modify.
    -->
    select SYS_CONFIG_ID, NAME, CUR_VALUE, VALUE_DESC
    from sys_config
  </select>
</mapper>